binary2strings.cp310-win_amd64.pyd
binary2strings-0.1.13.dist-info/LICENSE
binary2strings-0.1.13.dist-info/METADATA
binary2strings-0.1.13.dist-info/WHEEL
binary2strings-0.1.13.dist-info/top_level.txt
binary2strings-0.1.13.dist-info/RECORD
