Metadata-Version: 2.1
Name: binary2strings
Version: 0.1.13
Summary: Fast string extraction from binary buffers.
Home-page: https://github.com/glmcdona/binary2strings
Author: Geoff McDonald
Author-email: glmcdona@gmail.com
License: MIT
Requires-Python: >=3.7
License-File: LICENSE
